COPEX_high_rate_compression_quality_metrics/Kmeans_plus_plus_with_fixed_centroids_zhour.py
COPEX_high_rate_compression_quality_metrics/__init__.py
COPEX_high_rate_compression_quality_metrics/app.py
COPEX_high_rate_compression_quality_metrics/csv_converter.py
COPEX_high_rate_compression_quality_metrics/executable.py
COPEX_high_rate_compression_quality_metrics/global_variables.py
COPEX_high_rate_compression_quality_metrics/json_builder.py
COPEX_high_rate_compression_quality_metrics/json_converter.py
COPEX_high_rate_compression_quality_metrics/metrics.py
COPEX_high_rate_compression_quality_metrics/tasks.py
COPEX_high_rate_compression_quality_metrics/thematic.py
COPEX_high_rate_compression_quality_metrics/utils.py
COPEX_high_rate_compression_quality_metrics/lpips_model/alex.pth
COPEX_high_rate_compression_quality_metrics-0.5.5.dist-info/METADATA
COPEX_high_rate_compression_quality_metrics-0.5.5.dist-info/WHEEL
COPEX_high_rate_compression_quality_metrics-0.5.5.dist-info/top_level.txt
COPEX_high_rate_compression_quality_metrics-0.5.5.dist-info/RECORD
