Metadata-Version: 2.1
Name: COPEX-high-rate-compression-quality-metrics
Version: 0.5.5
Summary: COPEX high rate compression quality metrics
Home-page: https://github.com/VisioTerra/COPEX_high_rate_compression_quality_metrics
Author: VisioTerra
Author-email: info@visioterra.fr
Classifier: Programming Language :: Python :: 3
Classifier: License :: OSI Approved :: MIT License
Classifier: Operating System :: OS Independent
Requires-Python: >=3.9
Requires-Dist: importlib-metadata ==8.2.0
Requires-Dist: lpips ==0.1.4
Requires-Dist: matplotlib ==3.9.2
Requires-Dist: numpy ==1.26.4
Requires-Dist: scikit-image ==0.24.0
Requires-Dist: scikit-learn ==1.5.1
Requires-Dist: torch ==2.4.0
Requires-Dist: imagecodecs ==2024.6.1
